CryptoStrings/__init__.py
CryptoStrings/core.py
cryptostrings-1.1.1.dist-info/METADATA
cryptostrings-1.1.1.dist-info/WHEEL
cryptostrings-1.1.1.dist-info/top_level.txt
cryptostrings-1.1.1.dist-info/RECORD
