Metadata-Version: 2.4
Name: CryptoStrings
Version: 1.1.1
Summary: Cryptographically secure random generator for strings, numbers, passwords, API keys, and bytes
Author-email: Sammy Folkhome <support@vincio.cc>
License: GPL-3.0-or-later
Project-URL: Homepage, https://github.com/sammyfolkhome/CryptoStrings
Project-URL: Bug Tracker, https://github.com/sammyfolkhome/CryptoStrings/issues
Keywords: security,cryptography,random,token,password,api-key
Classifier: Development Status :: 5 - Production/Stable
Classifier: Intended Audience :: Developers
Classifier: Programming Language :: Python :: 3
Classifier: Programming Language :: Python :: 3.7
Classifier: Programming Language :: Python :: 3.8
Classifier: Programming Language :: Python :: 3.9
Classifier: Programming Language :: Python :: 3.10
Classifier: Programming Language :: Python :: 3.11
Classifier: Topic :: Security :: Cryptography
Classifier: Topic :: Software Development :: Libraries :: Python Modules
Requires-Python: >=3.7
